readms
