Metadata-Version: 1.0
Name: readms-cli
Version: 0.1.1
Summary: A cli tool for downloading manga in https://readms.net
Home-page: https://github.com/dslizardo/readms-cli
Author: Daniel Lizardo
Author-email: dslizardo@gmail.com
License: MIT
Keywords: readms cli manga
Platform: UNKNOWN
